enumtables/__init__.py
enumtables/alembic_ops/__init__.py
enumtables/alembic_ops/alembic_autogen.py
enumtables/alembic_ops/alembic_ops.py
enumtables/enum_table.py
enumtables/enum_type.py
gino_enum_tables-1.0.7.dist-info/LICENSE
gino_enum_tables-1.0.7.dist-info/WHEEL
gino_enum_tables-1.0.7.dist-info/METADATA
gino_enum_tables-1.0.7.dist-info/RECORD
