Metadata-Version: 2.1
Name: gino-enum-tables
Version: 1.0.7
Summary: Support for storing enum values in a table instead of a type
License: Apache-2.0
Keywords: enum,table,type,orm,sqlalchemy,python3
Author: Gazorby
Author-email: gazorby@pm.me
Classifier: License :: OSI Approved :: Apache Software License
Classifier: Programming Language :: Python :: 2
Classifier: Programming Language :: Python :: 2.7
Classifier: Programming Language :: Python :: 3
Classifier: Programming Language :: Python :: 3.4
Classifier: Programming Language :: Python :: 3.5
Classifier: Programming Language :: Python :: 3.6
Classifier: Programming Language :: Python :: 3.7
Classifier: Programming Language :: Python :: 3.8
Requires-Dist: sqlalchemy (>=1.3.18,<2.0.0)
